{
  "ABW": "High Income",
  "AFG": "Low Income",
  "AGO": "Lower Middle Income",
  "ALB": "Upper Middle Income",
  "AND": "High Income",
  "ARE": "High Income",
  "ARG": "Upper Middle Income",
  "ARM": "Upper Middle Income",
  "ASM": "High Income",
  "ATG": "High Income",
  "AUS": "High Income",
  "AUT": "High Income",
  "AZE": "Upper Middle Income",
  "BDI": "Low Income",
  "BEL": "High Income",
  "BEN": "Lower Middle Income",
  "BFA": "Low Income",
  "BGD": "Lower Middle Income",
  "BGR": "High Income",
  "BHR": "High Income",
  "BHS": "High Income",
  "BIH": "Upper Middle Income",
  "BLR": "Upper Middle Income",
  "BLZ": "Upper Middle Income",
  "BMU": "High Income",
  "BOL": "Lower Middle Income",
  "BRA": "Upper Middle Income",
  "BRB": "High Income",
  "BRN": "High Income",
  "BTN": "Lower Middle Income",
  "BWA": "Upper Middle Income",
  "CAF": "Low Income",
  "CAN": "High Income",
  "CHE": "High Income",
  "CHI": "High Income",
  "CHL": "High Income",
  "CHN": "Upper Middle Income",
  "CIV": "Lower Middle Income",
  "CMR": "Lower Middle Income",
  "COD": "Low Income",
  "COG": "Lower Middle Income",
  "COL": "Upper Middle Income",
  "COM": "Lower Middle Income",
  "CPV": "Upper Middle Income",
  "CRI": "High Income",
  "CUB": "Upper Middle Income",
  "CUW": "High Income",
  "CYM": "High Income",
  "CYP": "High Income",
  "CZE": "High Income",
  "DEU": "High Income",
  "DJI": "Lower Middle Income",
  "DMA": "Upper Middle Income",
  "DNK": "High Income",
  "DOM": "Upper Middle Income",
  "DZA": "Upper Middle Income",
  "ECU": "Upper Middle Income",
  "EGY": "Lower Middle Income",
  "ERI": "Low Income",
  "ESP": "High Income",
  "EST": "High Income",
  "FIN": "High Income",
  "FJI": "Upper Middle Income",
  "FRA": "High Income",
  "FRO": "High Income",
  "FSM": "Lower Middle Income",
  "GAB": "Upper Middle Income",
  "GBR": "High Income",
  "GEO": "Upper Middle Income",
  "GHA": "Lower Middle Income",
  "GIB": "High Income",
  "GIN": "Lower Middle Income",
  "GMB": "Low Income",
  "GNB": "Low Income",
  "GNQ": "Upper Middle Income",
  "GRC": "High Income",
  "GRD": "Upper Middle Income",
  "GRL": "High Income",
  "GTM": "Upper Middle Income",
  "GUM": "High Income",
  "GUY": "High Income",
  "HKG": "High Income",
  "HND": "Lower Middle Income",
  "HRV": "High Income",
  "HTI": "Lower Middle Income",
  "HUN": "High Income",
  "IDN": "Upper Middle Income",
  "IMN": "High Income",
  "IND": "Lower Middle Income",
  "IRL": "High Income",
  "IRN": "Upper Middle Income",
  "IRQ": "Upper Middle Income",
  "ISL": "High Income",
  "ISR": "High Income",
  "ITA": "High Income",
  "JAM": "Upper Middle Income",
  "JOR": "Lower Middle Income",
  "JPN": "High Income",
  "KAZ": "Upper Middle Income",
  "KEN": "Lower Middle Income",
  "KGZ": "Lower Middle Income",
  "KHM": "Lower Middle Income",
  "KIR": "Lower Middle Income",
  "KNA": "High Income",
  "KOR": "High Income",
  "KWT": "High Income",
  "LAO": "Lower Middle Income",
  "LBN": "Lower Middle Income",
  "LBR": "Low Income",
  "LBY": "Upper Middle Income",
  "LCA": "Upper Middle Income",
  "LIE": "High Income",
  "LKA": "Lower Middle Income",
  "LSO": "Lower Middle Income",
  "LTU": "High Income",
  "LUX": "High Income",
  "LVA": "High Income",
  "MAC": "High Income",
  "MAF": "High Income",
  "MAR": "Lower Middle Income",
  "MCO": "High Income",
  "MDA": "Upper Middle Income",
  "MDG": "Low Income",
  "MDV": "Upper Middle Income",
  "MEX": "Upper Middle Income",
  "MHL": "Upper Middle Income",
  "MKD": "Upper Middle Income",
  "MLI": "Low Income",
  "MLT": "High Income",
  "MMR": "Lower Middle Income",
  "MNE": "Upper Middle Income",
  "MNG": "Upper Middle Income",
  "MNP": "High Income",
  "MOZ": "Low Income",
  "MRT": "Lower Middle Income",
  "MUS": "Upper Middle Income",
  "MWI": "Low Income",
  "MYS": "Upper Middle Income",
  "NAM": "Lower Middle Income",
  "NCL": "High Income",
  "NER": "Low Income",
  "NGA": "Lower Middle Income",
  "NIC": "Lower Middle Income",
  "NLD": "High Income",
  "NOR": "High Income",
  "NPL": "Lower Middle Income",
  "NRU": "High Income",
  "NZL": "High Income",
  "OMN": "High Income",
  "PAK": "Lower Middle Income",
  "PAN": "High Income",
  "PER": "Upper Middle Income",
  "PHL": "Lower Middle Income",
  "PLW": "High Income",
  "PNG": "Lower Middle Income",
  "POL": "High Income",
  "PRI": "High Income",
  "PRK": "Low Income",
  "PRT": "High Income",
  "PRY": "Upper Middle Income",
  "PSE": "Lower Middle Income",
  "PYF": "High Income",
  "QAT": "High Income",
  "ROU": "High Income",
  "RUS": "High Income",
  "RWA": "Low Income",
  "SAU": "High Income",
  "SDN": "Low Income",
  "SEN": "Lower Middle Income",
  "SGP": "High Income",
  "SLB": "Lower Middle Income",
  "SLE": "Low Income",
  "SLV": "Upper Middle Income",
  "SMR": "High Income",
  "SOM": "Low Income",
  "SRB": "Upper Middle Income",
  "SSD": "Low Income",
  "STP": "Lower Middle Income",
  "SUR": "Upper Middle Income",
  "SVK": "High Income",
  "SVN": "High Income",
  "SWE": "High Income",
  "SWZ": "Lower Middle Income",
  "SXM": "High Income",
  "SYC": "High Income",
  "SYR": "Low Income",
  "TCA": "High Income",
  "TCD": "Low Income",
  "TGO": "Low Income",
  "THA": "Upper Middle Income",
  "TJK": "Lower Middle Income",
  "TKM": "Upper Middle Income",
  "TLS": "Lower Middle Income",
  "TON": "Upper Middle Income",
  "TTO": "High Income",
  "TUN": "Lower Middle Income",
  "TUR": "Upper Middle Income",
  "TUV": "Upper Middle Income",
  "TZA": "Lower Middle Income",
  "UGA": "Low Income",
  "UKR": "Upper Middle Income",
  "URY": "High Income",
  "USA": "High Income",
  "UZB": "Lower Middle Income",
  "VCT": "Upper Middle Income",
  "VGB": "High Income",
  "VIR": "High Income",
  "VNM": "Lower Middle Income",
  "VUT": "Lower Middle Income",
  "WSM": "Upper Middle Income",
  "XKX": "Upper Middle Income",
  "YEM": "Low Income",
  "ZAF": "Upper Middle Income",
  "ZMB": "Lower Middle Income",
  "ZWE": "Lower Middle Income"
}